wb_aicli/__init__.py
wb_aicli/main.py
wb_aicli-0.1.1.dist-info/LICENSE
wb_aicli-0.1.1.dist-info/METADATA
wb_aicli-0.1.1.dist-info/WHEEL
wb_aicli-0.1.1.dist-info/entry_points.txt
wb_aicli-0.1.1.dist-info/RECORD
